config_master/__init__.py
config_master/config_master.py
config_master/exceptions.py
configuration_master-0.0.1.dist-info/LICENSE
configuration_master-0.0.1.dist-info/METADATA
configuration_master-0.0.1.dist-info/WHEEL
configuration_master-0.0.1.dist-info/top_level.txt
configuration_master-0.0.1.dist-info/RECORD
