Metadata-Version: 2.1
Name: configuration-master
Version: 0.0.1
Summary: A package for configuration management
Home-page: https://github.com/RajeshKumar1490/config-master
Author: Rajesh Ganjikunta
Author-email: rajeshkumarganjikunta90@gmail.com
License-File: LICENSE
